LICENSE
MANIFEST.in
README.md
setup.cfg
setup.py
concierge_theme_pleio/__init__.py
concierge_theme_pleio/admin.py
concierge_theme_pleio/apps.py
concierge_theme_pleio/models.py
concierge_theme_pleio/settings.py
concierge_theme_pleio/tests.py
concierge_theme_pleio/views.py
concierge_theme_pleio/webpack-stats.json
concierge_theme_pleio.egg-info/PKG-INFO
concierge_theme_pleio.egg-info/SOURCES.txt
concierge_theme_pleio.egg-info/dependency_links.txt
concierge_theme_pleio.egg-info/top_level.txt
concierge_theme_pleio/migrations/__init__.py
concierge_theme_pleio/static/bundles/1dafe699fad5efe7df7bbb28cfd31519.woff
concierge_theme_pleio/static/bundles/6b15ad134ae76154ed277eeb6bde2eb8.ttf
concierge_theme_pleio/static/bundles/e17f1fb2d8212a65ee455b861a268255.svg
concierge_theme_pleio/static/bundles/f22699681491320346319be64d1e4cef.eot
concierge_theme_pleio/static/bundles/f6796e5c2bf2515cceae5e99c2deae77.woff2
concierge_theme_pleio/static/bundles/vendor.js
concierge_theme_pleio/static/bundles/web.css
concierge_theme_pleio/static/bundles/web.css.map
concierge_theme_pleio/static/bundles/web.js
concierge_theme_pleio/static/icons/account-alert.svg
concierge_theme_pleio/static/icons/arrow-right.svg
concierge_theme_pleio/static/icons/check.svg
concierge_theme_pleio/static/icons/chevron-left.svg
concierge_theme_pleio/static/icons/chevron-right.svg
concierge_theme_pleio/static/icons/chevron-up.svg
concierge_theme_pleio/static/icons/close.svg
concierge_theme_pleio/static/icons/email.svg
concierge_theme_pleio/static/icons/eye.svg
concierge_theme_pleio/static/icons/hamburger.svg
concierge_theme_pleio/static/icons/help-outline.svg
concierge_theme_pleio/static/icons/link.svg
concierge_theme_pleio/static/icons/lock-open.svg
concierge_theme_pleio/static/icons/lock-plus.svg
concierge_theme_pleio/static/icons/os-android.svg
concierge_theme_pleio/static/icons/os-apple.svg
concierge_theme_pleio/static/icons/person.svg
concierge_theme_pleio/static/icons/play.svg
concierge_theme_pleio/static/icons/search.svg
concierge_theme_pleio/static/icons/security.svg
concierge_theme_pleio/static/images/2fa.svg
concierge_theme_pleio/static/images/email-logo.png
