Metadata-Version: 1.2
Name: concierge-theme-pleio
Version: 0.9.1
Summary: Pleio theme for Concierge
Home-page: https://github.com/Pleio/concierge-theme-pleio
Maintainer: Pleio
Maintainer-email: support@pleio.nl
License: OSI Approved :: European Union Public Licence 1.1 (EUPL 1.1)
Platform: UNKNOWN
Classifier: Environment :: Web Environment
Classifier: Intended Audience :: Developers
Classifier: Operating System :: OS Independent
Classifier: Programming Language :: Python
Classifier: Programming Language :: Python :: 3.5
Classifier: Programming Language :: Python :: 3.6
